LICENSE
README.md
pyproject.toml
anonymity_api/__init__.py
anonymity_api/anonymity/__init__.py
anonymity_api/anonymity/_k_anonymity.py
anonymity_api/anonymity/_l_diversity.py
anonymity_api/anonymity/_rank_swapping.py
anonymity_api/anonymity/_rank_swapping_distribution.py
anonymity_api/anonymity/_suggestion.py
anonymity_api/anonymity/_t_closeness.py
anonymity_api/anonymity/_workload_aware.py
anonymity_api/anonymity/utils/__init__.py
anonymity_api/anonymity/utils/anon_functions.py
anonymity_api/anonymity/utils/aux_functions.py
anonymity_api/utility/__analysis.py
anonymity_api/utility/__init__.py
anonymity_api/utility/__metrics.py
anonymity_api/utility/utils/__init__.py
anonymity_api/utility/utils/aux_functions.py
anonymity_api/verify/__init__.py
anonymity_api/verify/_k_anonymity.py
anonymity_api/verify/_l_diversity.py
anonymity_api/verify/_t_closeness.py
anonymity_api/verify/utils/__init__.py
anonymity_api/verify/utils/aux_functions.py
anonymity_api-1.1.1.dist-info/METADATA
anonymity_api-1.1.1.dist-info/WHEEL
anonymity_api-1.1.1.dist-info/licenses/LICENSE
anonymity_api-1.1.1.dist-info/RECORD
