Metadata-Version: 2.4
Name: anonymity-api
Version: 1.1.1
Summary: Python library that offers conventional anonymization techniques, utility metrics, and verification methods.
Project-URL: source, https://github.com/farosilva0/anonymity_api
Project-URL: download, https://pypi.org/project/anonymity-api/#files
License-Expression: MIT
License-File: LICENSE
Classifier: Operating System :: OS Independent
Classifier: Programming Language :: Python
Classifier: Programming Language :: Python :: 3
Classifier: Programming Language :: Python :: 3.13
Classifier: Topic :: Security
Requires-Python: >=3.13
Requires-Dist: numpy>=2.2.5
Requires-Dist: pandas>=2.2.3
Requires-Dist: scipy>=1.15.3
Requires-Dist: sentence-transformers>=4.1.0
